coq_jupyter/__init__.py
coq_jupyter/__main__.py
coq_jupyter/coqtop.py
coq_jupyter/install.py
coq_jupyter/kernel.js
coq_jupyter/kernel.py
coq_jupyter/renderer.py
coq_jupyter-1.6.2.dist-info/LICENSE
coq_jupyter-1.6.2.dist-info/METADATA
coq_jupyter-1.6.2.dist-info/WHEEL
coq_jupyter-1.6.2.dist-info/top_level.txt
coq_jupyter-1.6.2.dist-info/RECORD
